TBG/CMD.py
TBG/__init__.py
TBG/default_help.py
TBG/fight_move.py
TBG/item.py
TBG/level.py
TBG/player.py
TBG/room.py
Futshane_TBG-1.0.0.dist-info/METADATA
Futshane_TBG-1.0.0.dist-info/WHEEL
Futshane_TBG-1.0.0.dist-info/top_level.txt
Futshane_TBG-1.0.0.dist-info/RECORD
