Metadata-Version: 2.1
Name: Futshane-TBG
Version: 1.0.0
Summary: This package provides simple tools for creating Text Based Games.
Home-page: https://github.com/ElLoko233/Text-Based-Game-Package
Author: Lelethu Futshane
License: UNKNOWN
Platform: UNKNOWN
Classifier: License :: OSI Approved :: MIT License
Classifier: Programming Language :: Python :: 3
Classifier: Programming Language :: Python :: 3.8
